codesphere/__init__.py
codesphere/api_client.py
codesphere/api_response.py
codesphere/client.py
codesphere/configuration.py
codesphere/exceptions.py
codesphere/py.typed
codesphere/rest.py
codesphere/.openapi-generator/FILES
codesphere/.openapi-generator/VERSION
codesphere/api/__init__.py
codesphere/api/domains_api.py
codesphere/api/metadata_api.py
codesphere/api/teams_api.py
codesphere/api/workspaces_api.py
codesphere/models/__init__.py
codesphere/models/domains_get_domain200_response.py
codesphere/models/domains_get_domain200_response_certificate_request_status.py
codesphere/models/domains_get_domain200_response_custom_config.py
codesphere/models/domains_get_domain200_response_dns_entries.py
codesphere/models/domains_get_domain200_response_domain_verification_status.py
codesphere/models/metadata_get_datacenters200_response_inner.py
codesphere/models/metadata_get_workspace_base_images200_response_inner.py
codesphere/models/metadata_get_workspace_plans200_response_inner.py
codesphere/models/metadata_get_workspace_plans200_response_inner_characteristics.py
codesphere/models/problem.py
codesphere/models/problem_data.py
codesphere/models/teams_create_team_request.py
codesphere/models/teams_get_team200_response.py
codesphere/models/teams_list_teams200_response_inner.py
codesphere/models/workspaces_create_workspace_request.py
codesphere/models/workspaces_execute_command200_response.py
codesphere/models/workspaces_execute_command_request.py
codesphere/models/workspaces_get_workspace200_response.py
codesphere/models/workspaces_get_workspace_status200_response.py
codesphere/models/workspaces_git_head200_response.py
codesphere/models/workspaces_list_env_vars200_response_inner.py
codesphere/models/workspaces_logs200_response.py
codesphere/models/workspaces_logs_get_response.py
codesphere/models/workspaces_logs_get_response_data_inner.py
codesphere/models/workspaces_pipeline_status200_response_inner.py
codesphere-0.2.27.dist-info/METADATA
codesphere-0.2.27.dist-info/WHEEL
codesphere-0.2.27.dist-info/licenses/LICENSE
codesphere-0.2.27.dist-info/RECORD
