Metadata-Version: 2.4
Name: codesphere
Version: 0.2.27
Summary: Use Codesphere within python scripts.
Project-URL: Homepage, https://codesphere.com/
Project-URL: Repository, https://github.com/Datata1/codesphere-python-sdk
Project-URL: Bug Tracker, https://github.com/Datata1/codesphere-python-sdk/issues
Author-email: Datata1 <jan-david.wiederstein@codesphere.com>
License-File: LICENSE
Classifier: Development Status :: 3 - Alpha
Classifier: Intended Audience :: Developers
Classifier: License :: OSI Approved :: MIT License
Classifier: Operating System :: OS Independent
Classifier: Programming Language :: Python :: 3
Classifier: Topic :: Software Development :: Libraries :: Python Modules
Requires-Python: >=3.12.9
Requires-Dist: aiohttp-retry>=2.9.1
Requires-Dist: aiohttp>=3.12.13
Requires-Dist: pydantic>=2.11.7
Requires-Dist: python-dateutil>=2.9.0.post0
Requires-Dist: typing-extensions>=4.14.0
Requires-Dist: urllib3>=2.4.0
